BoldLines/__init__.py
BoldLines/lines.py
BoldLines-0.1.1.dist-info/METADATA
BoldLines-0.1.1.dist-info/WHEEL
BoldLines-0.1.1.dist-info/top_level.txt
BoldLines-0.1.1.dist-info/RECORD
