Metadata-Version: 2.1
Name: BoldLines
Version: 0.1.1
Summary: BoldLines Python Package
Home-page: UNKNOWN
Author: krishna sonune
Author-email: krishnasonune87@gmail.com
License: UNKNOWN
Keywords: python,first package
Platform: UNKNOWN
Classifier: Development Status :: 3 - Alpha
Classifier: Intended Audience :: Education
Classifier: Programming Language :: Python :: 2
Classifier: Programming Language :: Python :: 3
Classifier: Operating System :: MacOS :: MacOS X
Classifier: Operating System :: Microsoft :: Windows
